.coveragerc
CHANGES.rst
MANIFEST.in
README.rst
development.ini
production.ini
setup.cfg
setup.py
pyramid_html_minifier/__init__.py
pyramid_html_minifier/config.py
pyramid_html_minifier/util.py
pyramid_html_minifier.egg-info/PKG-INFO
pyramid_html_minifier.egg-info/SOURCES.txt
pyramid_html_minifier.egg-info/dependency_links.txt
pyramid_html_minifier.egg-info/entry_points.txt
pyramid_html_minifier.egg-info/not-zip-safe
pyramid_html_minifier.egg-info/requires.txt
pyramid_html_minifier.egg-info/top_level.txt
pyramid_html_minifier/tests/test_html_renderer.py
pyramid_html_minifier/tests/fixtures/minimal.html
pyramid_html_minifier/tests/fixtures/pp.html
pyramid_html_minifier/tests/fixtures/withmacro.html
pyramid_html_minifier/tests/fixtures/app/withmacro.html
pyramid_html_minifier/tests/fixtures/mydist/withmacro.html