Metadata-Version: 1.1
Name: pyramid-html-minifier
Version: 0.1
Summary: pyramid_html_minifier
Home-page: https://github.com/davidemoro/pyramid_html_minifier
Author: Davide Moro
Author-email: davide.moro@gmail.com
License: UNKNOWN
Keywords: web pyramid pylons
Platform: UNKNOWN
Classifier: Programming Language :: Python
Classifier: Framework :: Pyramid
Classifier: Topic :: Internet :: WWW/HTTP
Classifier: Topic :: Internet :: WWW/HTTP :: WSGI :: Application
